23andme_to_vcf/__init__.py
23andme_to_vcf/driver.py
23andme_to_vcf-0.0.3.data/scripts/23andme-to-vcf
23andme_to_vcf-0.0.3.data/scripts/23tovcf
23andme_to_vcf-0.0.3.dist-info/DESCRIPTION.rst
23andme_to_vcf-0.0.3.dist-info/METADATA
23andme_to_vcf-0.0.3.dist-info/RECORD
23andme_to_vcf-0.0.3.dist-info/WHEEL
23andme_to_vcf-0.0.3.dist-info/metadata.json
23andme_to_vcf-0.0.3.dist-info/top_level.txt
_23andme_to_vcf/__init__.py
_23andme_to_vcf/driver.py
